images_to_zarr/CLI.py
images_to_zarr/__init__.py
images_to_zarr/__main__.py
images_to_zarr/append.py
images_to_zarr/convert.py
images_to_zarr/display_sample_images.py
images_to_zarr/inspect.py
images_to_zarr-0.3.5.dist-info/licenses/LICENSE
images_to_zarr-0.3.5.dist-info/METADATA
images_to_zarr-0.3.5.dist-info/WHEEL
images_to_zarr-0.3.5.dist-info/entry_points.txt
images_to_zarr-0.3.5.dist-info/top_level.txt
images_to_zarr-0.3.5.dist-info/RECORD
