Metadata-Version: 2.4
Name: images_to_zarr
Version: 0.3.5
Summary: Tiny Python module to bulk-convert large amounts of images into zarr files
Author-email: Pablo Gómez <contact@pablo-gomez.net>
License: (GPL-3.0 OR MIT) License
Project-URL: Homepage, https://github.com/gomezzz/images_to_zarr
Project-URL: Repository, https://github.com/gomezzz/images_to_zarr
Project-URL: Issues, https://github.com/gomezzz/images_to_zarr/issues
Classifier: Development Status :: 4 - Beta
Classifier: Intended Audience :: Science/Research
Classifier: License :: OSI Approved :: MIT License
Classifier: Programming Language :: Python :: 3
Classifier: Programming Language :: Python :: 3.10
Classifier: Topic :: Scientific/Engineering
Classifier: Topic :: Scientific/Engineering :: Astronomy
Requires-Python: >=3.10
License-File: LICENSE
Requires-Dist: astropy
Requires-Dist: click
Requires-Dist: imageio>=2.20.0
Requires-Dist: loguru
Requires-Dist: numpy
Requires-Dist: pandas
Requires-Dist: scikit-image
Requires-Dist: tqdm
Requires-Dist: zarr>=3.0.0a5
Provides-Extra: dev
Requires-Dist: pytest; extra == "dev"
Requires-Dist: pytest-cov; extra == "dev"
Requires-Dist: black; extra == "dev"
Requires-Dist: flake8; extra == "dev"
Dynamic: license-file
